streamlit_supabase_auth_flow/__init__.py
streamlit_supabase_auth_flow/auth.py
streamlit_supabase_auth_flow/py.typed
streamlit_supabase_auth_flow-0.0.2.dist-info/WHEEL
streamlit_supabase_auth_flow-0.0.2.dist-info/METADATA
streamlit_supabase_auth_flow-0.0.2.dist-info/RECORD
