Metadata-Version: 2.3
Name: streamlit-supabase-auth-flow
Version: 0.0.2
Summary: Simple Supabase auth for streamlit using implicit flow.
Author: Adamos Spanashis
Author-email: Adamos Spanashis <adamingas@gmail.com>
Requires-Dist: streamlit>=1.48.1
Requires-Dist: streamlit-url-fragments>=0.1.2
Requires-Python: >=3.13
